backend_shim.py
pants_wheel-0.0.125.dist-info/METADATA
pants_wheel-0.0.125.dist-info/WHEEL
pants_wheel-0.0.125.dist-info/top_level.txt
pants_wheel-0.0.125.dist-info/RECORD
