Metadata-Version: 2.4
Name: pants_wheel
Version: 0.0.125
Summary: Pants project
Author-email: ksajere <author@example.com>
Maintainer-email: Best Dev in the world <maintainer@example.com>
Project-URL: Homepage, https://github.com/ksajere
Keywords: sample,setuptools,development
Classifier: Programming Language :: Python :: 3.9
Classifier: Programming Language :: Python :: 3.10
Requires-Python: >=3.9
